straug/__init__.py
straug/blur.py
straug/camera.py
straug/geometry.py
straug/noise.py
straug/ops.py
straug/pattern.py
straug/process.py
straug/warp.py
straug/weather.py
straug/frost/__init__.py
straug/frost/frost1.png
straug/frost/frost2.png
straug/frost/frost3.png
straug/frost/frost4.jpg
straug/frost/frost5.jpg
straug/frost/frost6.jpg
straug-0.1.2.dist-info/LICENSE
straug-0.1.2.dist-info/METADATA
straug-0.1.2.dist-info/WHEEL
straug-0.1.2.dist-info/top_level.txt
straug-0.1.2.dist-info/RECORD
