Metadata-Version: 2.1
Name: straug
Version: 0.1.2
Summary: Data Augmentation for STR
Home-page: https://github.com/roatienza/straug
Author: Rowel Atienza
Author-email: rowel@eee.upd.edu.ph
License: Apache
Keywords: computer vision,scene text recognition,ocr,data augmentation
Platform: UNKNOWN
Classifier: Development Status :: 4 - Beta
Classifier: Topic :: Scientific/Engineering :: Artificial Intelligence
Classifier: Intended Audience :: Developers
Classifier: License :: OSI Approved :: Apache Software License
Classifier: Programming Language :: Python :: 3
License-File: LICENSE
Requires-Dist: torchvision
Requires-Dist: magickwand
Requires-Dist: pillow
Requires-Dist: opencv-python
Requires-Dist: opencv-contrib-python
Requires-Dist: scikit-image
Requires-Dist: numpy
Requires-Dist: Wand
